{
	"favorites": [
		"{id:\"ftbteams:my_team\",json:'{\"group\":\"ftblibrary:info\",\"icon\":\"ftbteams:textures/teams.png\",\"x\":0,\"click\":\"ftbteams:open_gui\",\"loading_screen\":true}',type:\"ftblibrary:sidebar_button\"}",
		"{id:\"ftbquests:quests\",json:'{\"group\":\"ftblibrary:info\",\"icon\":\"ftbquests:item/book\",\"x\":610,\"click\":\"ftbquests:open_gui\",\"required_server_mods\":[\"ftbquests\"],\"custom_text\":true}',type:\"ftblibrary:sidebar_button\"}",
		"{id:\"ftbessentials:trash_can\",json:'{\"group\":\"ftblibrary:util\",\"icon\":\"ftblibrary:icons/bin\",\"x\":150,\"click\":\"command:/trashcan\",\"required_server_mods\":[\"ftbessentials\"]}',type:\"ftblibrary:sidebar_button\"}",
		"{id:\"ftbchunks:chunks\",json:'{\"group\":\"ftblibrary:util\",\"icon\":\"ftblibrary:icons/map\",\"x\":310,\"click\":\"ftbchunks:open_gui\"}',type:\"ftblibrary:sidebar_button\"}",
		"{id:\"ftblibrary:toggle.gamemode\",json:'{\"group\":\"ftblibrary:cheat\",\"icon\":[\"ftblibrary:icons/blue_button\",\"ftblibrary:textures/icons/toggle_gamemode.png\"],\"x\":100,\"click\":\"command:/ftblibrary gamemode\",\"hide_with_nei\":true,\"requires_op\":true}',type:\"ftblibrary:sidebar_button\"}",
		"{data:{Count:1b,id:\"naturesaura:offering_table\",type:\"minecraft:item\"},type:\"roughlyenoughitems:entry_stack\"}",
		"{data:{Count:1b,id:\"kubejs:tier_1_mechanical_alloy_robot_arm\",type:\"minecraft:item\"},type:\"roughlyenoughitems:entry_stack\"}",
		"{data:{Count:1b,id:\"modularrouters:blank_upgrade\",type:\"minecraft:item\"},type:\"roughlyenoughitems:entry_stack\"}",
		"{data:{Count:1b,id:\"minecraft:smooth_stone_slab\",type:\"minecraft:item\"},type:\"roughlyenoughitems:entry_stack\"}",
		"{data:{Count:1b,id:\"pneumaticcraft:vortex_tube\",type:\"minecraft:item\"},type:\"roughlyenoughitems:entry_stack\"}",
		"{data:{Count:1b,id:\"pneumaticcraft:heat_sink\",type:\"minecraft:item\"},type:\"roughlyenoughitems:entry_stack\"}",
		"{data:{Count:1b,id:\"pneumaticcraft:heat_frame\",type:\"minecraft:item\"},type:\"roughlyenoughitems:entry_stack\"}",
		"{data:{Count:1b,id:\"thermal:signalum_dust\",type:\"minecraft:item\"},type:\"roughlyenoughitems:entry_stack\"}",
		"{data:{Count:1b,id:\"powah:capacitor_blazing\",type:\"minecraft:item\"},type:\"roughlyenoughitems:entry_stack\"}",
		"{data:{Count:1b,id:\"powah:capacitor_basic\",type:\"minecraft:item\"},type:\"roughlyenoughitems:entry_stack\"}",
		"{data:{Count:1b,id:\"solarflux:blazing_coating\",type:\"minecraft:item\"},type:\"roughlyenoughitems:entry_stack\"}",
		"{data:{Count:1b,id:\"botania:quartz_blaze\",type:\"minecraft:item\"},type:\"roughlyenoughitems:entry_stack\"}",
		"{data:{Count:1b,id:\"ars_nouveau:earth_essence\",type:\"minecraft:item\"},type:\"roughlyenoughitems:entry_stack\"}",
		"{data:{Count:1b,id:\"pneumaticcraft:thermopneumatic_processing_plant\",type:\"minecraft:item\"},type:\"roughlyenoughitems:entry_stack\"}",
		"{data:{Count:1b,id:\"minecraft:dragon_head\",type:\"minecraft:item\"},type:\"roughlyenoughitems:entry_stack\"}",
		"{data:{Count:1b,id:\"forbidden_arcanus:mystical_dagger\",tag:{Damage:0},type:\"minecraft:item\"},type:\"roughlyenoughitems:entry_stack\"}",
		"{data:{Amount:1000,FluidName:\"pneumaticcraft:plastic\",type:\"minecraft:fluid\"},type:\"roughlyenoughitems:entry_stack\"}",
		"{data:{Count:1b,id:\"create:brass_casing\",type:\"minecraft:item\"},type:\"roughlyenoughitems:entry_stack\"}",
		"{data:{Count:1b,id:\"kubejs:brass_cog_block\",type:\"minecraft:item\"},type:\"roughlyenoughitems:entry_stack\"}",
		"{data:{Count:1b,id:\"compressedcreativity:engine_rotor\",type:\"minecraft:item\"},type:\"roughlyenoughitems:entry_stack\"}",
		"{data:{Count:1b,id:\"kubejs:compressed_steel_component\",type:\"minecraft:item\"},type:\"roughlyenoughitems:entry_stack\"}",
		"{data:{Count:1b,id:\"ae2:blank_pattern\",type:\"minecraft:item\"},type:\"roughlyenoughitems:entry_stack\"}",
		"{data:{Count:1b,id:\"ae2additions:pattern_provider_2th\",type:\"minecraft:item\"},type:\"roughlyenoughitems:entry_stack\"}",
		"{data:{Count:1b,id:\"pneumaticcraft:amadron_tablet\",type:\"minecraft:item\"},type:\"roughlyenoughitems:entry_stack\"}",
		"{data:{Count:1b,id:\"pneumaticcraft:charging_station\",type:\"minecraft:item\"},type:\"roughlyenoughitems:entry_stack\"}",
		"{data:{Count:1b,id:\"pneumaticcraft:gps_tool\",type:\"minecraft:item\"},type:\"roughlyenoughitems:entry_stack\"}",
		"{data:{Amount:1000,FluidName:\"pneumaticcraft:etching_acid\",type:\"minecraft:fluid\"},type:\"roughlyenoughitems:entry_stack\"}",
		"{data:{Count:1b,id:\"pneumaticcraft:empty_pcb\",type:\"minecraft:item\"},type:\"roughlyenoughitems:entry_stack\"}",
		"{data:{Count:1b,id:\"thermal:electrum_block\",type:\"minecraft:item\"},type:\"roughlyenoughitems:entry_stack\"}",
		"{data:{Count:1b,id:\"mbm2:flotation\",type:\"minecraft:item\"},type:\"roughlyenoughitems:entry_stack\"}",
		"{data:{Count:1b,id:\"pneumaticcraft:uv_light_box\",type:\"minecraft:item\"},type:\"roughlyenoughitems:entry_stack\"}",
		"{data:{Count:1b,id:\"minecraft:emerald\",type:\"minecraft:item\"},type:\"roughlyenoughitems:entry_stack\"}",
		"{data:{Count:1b,id:\"pneumaticcraft:drone\",type:\"minecraft:item\"},type:\"roughlyenoughitems:entry_stack\"}",
		"{data:{Count:1b,id:\"pneumaticcraft:programmer\",type:\"minecraft:item\"},type:\"roughlyenoughitems:entry_stack\"}",
		"{data:{Count:1b,id:\"pneumaticcraft:air_compressor\",type:\"minecraft:item\"},type:\"roughlyenoughitems:entry_stack\"}",
		"{data:{Count:1b,id:\"powah:dielectric_casing\",type:\"minecraft:item\"},type:\"roughlyenoughitems:entry_stack\"}",
		"{data:{Count:1b,id:\"pneumaticcraft:transistor\",type:\"minecraft:item\"},type:\"roughlyenoughitems:entry_stack\"}",
		"{data:{Count:1b,id:\"pneumaticcraft:capacitor\",type:\"minecraft:item\"},type:\"roughlyenoughitems:entry_stack\"}",
		"{data:{Count:1b,id:\"kubejs:tier_2_electrical_alloy_wire\",type:\"minecraft:item\"},type:\"roughlyenoughitems:entry_stack\"}",
		"{data:{Count:1b,id:\"kubejs:lead_sheet\",type:\"minecraft:item\"},type:\"roughlyenoughitems:entry_stack\"}",
		"{data:{Count:1b,id:\"projectred_core:silicon\",type:\"minecraft:item\"},type:\"roughlyenoughitems:entry_stack\"}",
		"{data:{Count:1b,id:\"ae2:controller\",type:\"minecraft:item\"},type:\"roughlyenoughitems:entry_stack\"}",
		"{data:{Count:1b,id:\"lazierae2:carbonic_fluix_dust\",type:\"minecraft:item\"},type:\"roughlyenoughitems:entry_stack\"}",
		"{data:{Count:1b,id:\"ae2:fluix_smart_dense_cable\",type:\"minecraft:item\"},type:\"roughlyenoughitems:entry_stack\"}",
		"{data:{Count:1b,id:\"ae2:memory_card\",tag:{},type:\"minecraft:item\"},type:\"roughlyenoughitems:entry_stack\"}",
		"{data:{Count:1b,id:\"ae2:me_p2p_tunnel\",type:\"minecraft:item\"},type:\"roughlyenoughitems:entry_stack\"}",
		"{data:{Count:1b,id:\"ae2:molecular_assembler\",type:\"minecraft:item\"},type:\"roughlyenoughitems:entry_stack\"}",
		"{data:{Count:1b,id:\"thermal:lumium_dust\",type:\"minecraft:item\"},type:\"roughlyenoughitems:entry_stack\"}",
		"{data:{Count:1b,id:\"ae2:formation_core\",type:\"minecraft:item\"},type:\"roughlyenoughitems:entry_stack\"}",
		"{data:{Count:1b,id:\"elementalcraft:fine_water_gem\",type:\"minecraft:item\"},type:\"roughlyenoughitems:entry_stack\"}",
		"{data:{Count:1b,id:\"powah:crystal_blazing\",type:\"minecraft:item\"},type:\"roughlyenoughitems:entry_stack\"}",
		"{data:{Count:1b,id:\"immersiveengineering:dynamo\",type:\"minecraft:item\"},type:\"roughlyenoughitems:entry_stack\"}",
		"{data:{Count:1b,id:\"immersiveengineering:windmill\",type:\"minecraft:item\"},type:\"roughlyenoughitems:entry_stack\"}",
		"{data:{Count:1b,id:\"functionalstorage:storage_controller\",type:\"minecraft:item\"},type:\"roughlyenoughitems:entry_stack\"}",
		"{data:{Count:1b,id:\"powah:furnator_blazing\",type:\"minecraft:item\"},type:\"roughlyenoughitems:entry_stack\"}",
		"{data:{Count:1b,id:\"kubejs:pressurized_aluminum_alloy_ingot\",type:\"minecraft:item\"},type:\"roughlyenoughitems:entry_stack\"}",
		"{data:{Count:1b,id:\"ae2things:crystal_growth\",type:\"minecraft:item\"},type:\"roughlyenoughitems:entry_stack\"}",
		"{data:{Count:1b,id:\"ae2:wireless_crafting_terminal\",type:\"minecraft:item\"},type:\"roughlyenoughitems:entry_stack\"}",
		"{data:{Count:1b,id:\"ae2:security_station\",type:\"minecraft:item\"},type:\"roughlyenoughitems:entry_stack\"}",
		"{data:{Count:1b,id:\"ae2:cell_component_16k\",type:\"minecraft:item\"},type:\"roughlyenoughitems:entry_stack\"}",
		"{data:{Count:1b,id:\"ae2:cell_component_4k\",type:\"minecraft:item\"},type:\"roughlyenoughitems:entry_stack\"}",
		"{data:{Count:1b,id:\"ae2:cell_component_1k\",type:\"minecraft:item\"},type:\"roughlyenoughitems:entry_stack\"}",
		"{data:{Count:1b,id:\"extendedcrafting:black_iron_slate\",type:\"minecraft:item\"},type:\"roughlyenoughitems:entry_stack\"}",
		"{data:{Count:1b,id:\"pneumaticcraft:plastic\",type:\"minecraft:item\"},type:\"roughlyenoughitems:entry_stack\"}",
		"{data:{Count:1b,id:\"pneumaticcraft:programming_puzzle\",type:\"minecraft:item\"},type:\"roughlyenoughitems:entry_stack\"}",
		"{data:{Count:1b,id:\"modularrouters:blank_module\",type:\"minecraft:item\"},type:\"roughlyenoughitems:entry_stack\"}",
		"{data:{Count:1b,id:\"kubejs:tier_2_electrical_alloy_plate\",type:\"minecraft:item\"},type:\"roughlyenoughitems:entry_stack\"}",
		"{data:{Count:1b,id:\"kubejs:unfinished_logic_unit\",type:\"minecraft:item\"},type:\"roughlyenoughitems:entry_stack\"}",
		"{data:{Count:1b,id:\"thermal:rf_coil\",type:\"minecraft:item\"},type:\"roughlyenoughitems:entry_stack\"}",
		"{data:{Count:1b,id:\"thermal:redstone_servo\",type:\"minecraft:item\"},type:\"roughlyenoughitems:entry_stack\"}",
		"{data:{Count:1b,id:\"thermal:upgrade_augment_1\",type:\"minecraft:item\"},type:\"roughlyenoughitems:entry_stack\"}",
		"{data:{Count:1b,id:\"modularrouters:modular_router\",type:\"minecraft:item\"},type:\"roughlyenoughitems:entry_stack\"}",
		"{data:{Count:1b,id:\"travel_anchors:travel_anchor\",type:\"minecraft:item\"},type:\"roughlyenoughitems:entry_stack\"}",
		"{data:{Count:1b,id:\"create:fluid_tank\",type:\"minecraft:item\"},type:\"roughlyenoughitems:entry_stack\"}",
		"{data:{Count:1b,id:\"hostilenetworks:empty_prediction\",type:\"minecraft:item\"},type:\"roughlyenoughitems:entry_stack\"}",
		"{data:{Count:1b,id:\"tconstruct:seared_brick\",type:\"minecraft:item\"},type:\"roughlyenoughitems:entry_stack\"}",
		"{data:{Count:1b,id:\"kubejs:coke_oven_brick\",type:\"minecraft:item\"},type:\"roughlyenoughitems:entry_stack\"}",
		"{data:{Count:1b,id:\"create:cinder_flour\",type:\"minecraft:item\"},type:\"roughlyenoughitems:entry_stack\"}",
		"{data:{Count:1b,id:\"minecraft:magma_block\",type:\"minecraft:item\"},type:\"roughlyenoughitems:entry_stack\"}",
		"{data:{Count:1b,id:\"create:scoria\",type:\"minecraft:item\"},type:\"roughlyenoughitems:entry_stack\"}",
		"{data:{Count:1b,id:\"reliquary:molten_core\",type:\"minecraft:item\"},type:\"roughlyenoughitems:entry_stack\"}",
		"{data:{Count:1b,id:\"mbm2:fusion_reactor\",type:\"minecraft:item\"},type:\"roughlyenoughitems:entry_stack\"}",
		"{data:{Count:1b,id:\"extendedcrafting:luminessence\",type:\"minecraft:item\"},type:\"roughlyenoughitems:entry_stack\"}",
		"{data:{Count:1b,id:\"naturesaura:conversion_catalyst\",type:\"minecraft:item\"},type:\"roughlyenoughitems:entry_stack\"}",
		"{data:{Count:1b,id:\"botania:alchemy_catalyst\",type:\"minecraft:item\"},type:\"roughlyenoughitems:entry_stack\"}",
		"{data:{Count:1b,id:\"multiblocked:fluid_output\",type:\"minecraft:item\"},type:\"roughlyenoughitems:entry_stack\"}",
		"{data:{Count:1b,id:\"multiblocked:item_input\",type:\"minecraft:item\"},type:\"roughlyenoughitems:entry_stack\"}",
		"{data:{Count:1b,id:\"laserio:laser_node\",type:\"minecraft:item\"},type:\"roughlyenoughitems:entry_stack\"}",
		"{data:{Count:1b,id:\"kubejs:luminite\",type:\"minecraft:item\"},type:\"roughlyenoughitems:entry_stack\"}",
		"{data:{Count:1b,id:\"chemlib:phosphorus\",type:\"minecraft:item\"},type:\"roughlyenoughitems:entry_stack\"}",
		"{data:{Count:1b,id:\"thermal:oil_red_sand\",type:\"minecraft:item\"},type:\"roughlyenoughitems:entry_stack\"}",
		"{data:{Count:1b,id:\"kubejs:luminite_dust\",type:\"minecraft:item\"},type:\"roughlyenoughitems:entry_stack\"}",
		"{data:{Count:1b,id:\"chemlib:germanium\",type:\"minecraft:item\"},type:\"roughlyenoughitems:entry_stack\"}",
		"{data:{Count:1b,id:\"ars_nouveau:ritual_wilden_summon\",type:\"minecraft:item\"},type:\"roughlyenoughitems:entry_stack\"}",
		"{data:{Count:1b,id:\"elementalcraft:air_silk\",type:\"minecraft:item\"},type:\"roughlyenoughitems:entry_stack\"}",
		"{data:{Count:1b,id:\"forbidden_arcanus:darkstone_pedestal\",type:\"minecraft:item\"},type:\"roughlyenoughitems:entry_stack\"}",
		"{data:{Count:1b,id:\"elementalcraft:solar_synthesizer\",type:\"minecraft:item\"},type:\"roughlyenoughitems:entry_stack\"}",
		"{data:{Count:1b,id:\"elementalcraft:container\",type:\"minecraft:item\"},type:\"roughlyenoughitems:entry_stack\"}",
		"{data:{Count:1b,id:\"elementalcraft:pedestal_fire\",type:\"minecraft:item\"},type:\"roughlyenoughitems:entry_stack\"}",
		"{data:{Amount:1000,FluidName:\"kubejs:volatile_elemental_mixture\",type:\"minecraft:fluid\"},type:\"roughlyenoughitems:entry_stack\"}",
		"{data:{Count:1b,id:\"elementalcraft:pristine_fire_gem\",type:\"minecraft:item\"},type:\"roughlyenoughitems:entry_stack\"}",
		"{data:{Count:1b,id:\"elementalcraft:pristine_water_gem\",type:\"minecraft:item\"},type:\"roughlyenoughitems:entry_stack\"}",
		"{data:{Count:1b,id:\"elementalcraft:pristine_air_gem\",type:\"minecraft:item\"},type:\"roughlyenoughitems:entry_stack\"}",
		"{data:{Count:1b,id:\"elementalcraft:pristine_earth_gem\",type:\"minecraft:item\"},type:\"roughlyenoughitems:entry_stack\"}",
		"{data:{Count:1b,id:\"elementalcraft:crude_air_gem\",type:\"minecraft:item\"},type:\"roughlyenoughitems:entry_stack\"}",
		"{data:{Count:1b,id:\"elementalcraft:crude_water_gem\",type:\"minecraft:item\"},type:\"roughlyenoughitems:entry_stack\"}",
		"{data:{Count:1b,id:\"elementalcraft:crude_fire_gem\",type:\"minecraft:item\"},type:\"roughlyenoughitems:entry_stack\"}",
		"{data:{Count:1b,id:\"elementalcraft:crude_earth_gem\",type:\"minecraft:item\"},type:\"roughlyenoughitems:entry_stack\"}",
		"{data:{Count:1b,id:\"kubejs:catalyst_gem\",type:\"minecraft:item\"},type:\"roughlyenoughitems:entry_stack\"}",
		"{data:{Count:1b,id:\"mbm2:elemental_stabilizer\",type:\"minecraft:item\"},type:\"roughlyenoughitems:entry_stack\"}",
		"{data:{Count:1b,id:\"botania:bifrost_perm\",type:\"minecraft:item\"},type:\"roughlyenoughitems:entry_stack\"}",
		"{data:{Count:1b,id:\"kubejs:transmuted_casing\",type:\"minecraft:item\"},type:\"roughlyenoughitems:entry_stack\"}",
		"{data:{Count:1b,id:\"kubejs:reflector\",type:\"minecraft:item\"},type:\"roughlyenoughitems:entry_stack\"}",
		"{data:{Count:1b,id:\"solarflux:photovoltaic_cell_3\",type:\"minecraft:item\"},type:\"roughlyenoughitems:entry_stack\"}",
		"{data:{Count:1b,id:\"solarflux:mirror\",type:\"minecraft:item\"},type:\"roughlyenoughitems:entry_stack\"}",
		"{data:{Count:1b,id:\"kubejs:lapatron_orb_full\",type:\"minecraft:item\"},type:\"roughlyenoughitems:entry_stack\"}",
		"{data:{Count:1b,id:\"kubejs:tier2_casing\",type:\"minecraft:item\"},type:\"roughlyenoughitems:entry_stack\"}"
	],
	"hiddenFavorites": [],
	"displays": [
		"{DisplayHistoryCategory:\"multiblocked:mixer\",DisplayHistoryContains:0b,DisplayHistoryUUID:\"4994bd5b-3040-4e8e-a262-a182c140d180\"}"
	]
}