{"net.minecraftforge.event.entity.player.PlayerEvent$LoadFromFile":"net.minecraftforge.event.entity.player.PlayerEvent$LoadFromFile","net.minecraftforge.client.event.EntityViewRenderEvent$FogColors":"net.minecraftforge.client.event.EntityViewRenderEvent$FogColors","be.florens.expandability.api.forge.PlayerSwimEvent":"be.florens.expandability.api.forge.PlayerSwimEvent","net.minecraftforge.event.entity.player.PlayerInteractEvent$RightClickItem":"net.minecraftforge.event.entity.player.PlayerInteractEvent$RightClickItem","net.minecraftforge.event.village.VillagerTradesEvent":"net.minecraftforge.event.village.VillagerTradesEvent","io.github.noeppi_noeppi.libx.event.RandomTickEvent$Fluid":"io.github.noeppi_noeppi.libx.event.RandomTickEvent$Fluid","net.minecraftforge.event.entity.player.PlayerEvent$StopTracking":"net.minecraftforge.event.entity.player.PlayerEvent$StopTracking","net.minecraftforge.client.event.ScreenEvent$DrawScreenEvent$Post":"net.minecraftforge.client.event.ScreenEvent$DrawScreenEvent$Post","net.minecraftforge.event.entity.living.LivingDamageEvent":"net.minecraftforge.event.entity.living.LivingDamageEvent","net.minecraftforge.client.event.EntityViewRenderEvent$CameraSetup":"net.minecraftforge.client.event.EntityViewRenderEvent$CameraSetup","net.minecraftforge.client.event.InputEvent$MouseScrollEvent":"net.minecraftforge.client.event.InputEvent$MouseScrollEvent","com.blakebr0.cucumber.event.RegisterRecipesEvent":"com.blakebr0.cucumber.event.RegisterRecipesEvent","net.minecraftforge.event.RegisterCommandsEvent":"net.minecraftforge.event.RegisterCommandsEvent","net.minecraftforge.client.event.sound.PlayStreamingSourceEvent":"net.minecraftforge.client.event.sound.PlayStreamingSourceEvent","net.minecraftforge.event.entity.living.LivingSpawnEvent$AllowDespawn":"net.minecraftforge.event.entity.living.LivingSpawnEvent$AllowDespawn","net.minecraftforge.event.entity.player.PlayerEvent$PlayerLoggedInEvent":"net.minecraftforge.event.entity.player.PlayerEvent$PlayerLoggedInEvent","slimeknights.tconstruct.library.modifiers.ModifierManager$ModifiersLoadedEvent":"slimeknights.tconstruct.library.modifiers.ModifierManager$ModifiersLoadedEvent","net.mehvahdjukaar.selene.villager_ai.VillagerBrainEvent":"net.mehvahdjukaar.selene.villager_ai.VillagerBrainEvent","net.minecraftforge.client.event.ScreenEvent$MouseClickedEvent$Pre":"net.minecraftforge.client.event.ScreenEvent$MouseClickedEvent$Pre","sirttas.dpanvil.api.event.DataPackReloadCompleteEvent":"sirttas.dpanvil.api.event.DataPackReloadCompleteEvent","net.minecraftforge.client.event.EntityViewRenderEvent$RenderFogEvent":"net.minecraftforge.client.event.EntityViewRenderEvent$RenderFogEvent","net.minecraftforge.event.TagsUpdatedEvent":"net.minecraftforge.event.TagsUpdatedEvent","net.minecraftforge.event.entity.living.LivingEvent$LivingVisibilityEvent":"net.minecraftforge.event.entity.living.LivingEvent$LivingVisibilityEvent","net.minecraftforge.client.event.ScreenEvent$MouseReleasedEvent$Post":"net.minecraftforge.client.event.ScreenEvent$MouseReleasedEvent$Post","net.minecraftforge.event.entity.player.ItemTooltipEvent":"net.minecraftforge.event.entity.player.ItemTooltipEvent","net.minecraftforge.event.entity.living.LivingGetProjectileEvent":"net.minecraftforge.event.entity.living.LivingGetProjectileEvent","org.zeith.hammerlib.event.client.ClientLoadedInEvent":"org.zeith.hammerlib.event.client.ClientLoadedInEvent","net.roguelogix.phosphophyllite.event.ReloadDataEvent":"net.roguelogix.phosphophyllite.event.ReloadDataEvent","net.minecraftforge.event.entity.EntityLeaveWorldEvent":"net.minecraftforge.event.entity.EntityLeaveWorldEvent","com.github.alexthe666.citadel.client.event.EventPosePlayerHand":"com.github.alexthe666.citadel.client.event.EventPosePlayerHand","net.minecraftforge.client.event.DrawSelectionEvent$HighlightBlock":"net.minecraftforge.client.event.DrawSelectionEvent$HighlightBlock","net.minecraftforge.event.entity.EntityMobGriefingEvent":"net.minecraftforge.event.entity.EntityMobGriefingEvent","net.minecraftforge.client.event.RenderGameOverlayEvent$PostLayer":"net.minecraftforge.client.event.RenderGameOverlayEvent$PostLayer","net.minecraftforge.event.world.WorldEvent$CreateSpawnPosition":"net.minecraftforge.event.world.WorldEvent$CreateSpawnPosition","net.minecraftforge.client.event.InputEvent$ClickInputEvent":"net.minecraftforge.client.event.InputEvent$ClickInputEvent","net.minecraftforge.client.event.ContainerScreenEvent$DrawBackground":"net.minecraftforge.client.event.ContainerScreenEvent$DrawBackground","net.minecraftforge.client.event.RenderGameOverlayEvent$Post":"net.minecraftforge.client.event.RenderGameOverlayEvent$Post","net.minecraftforge.event.entity.PlaySoundAtEntityEvent":"net.minecraftforge.event.entity.PlaySoundAtEntityEvent","net.minecraftforge.event.OnDatapackSyncEvent":"net.minecraftforge.event.OnDatapackSyncEvent","net.minecraftforge.client.event.ScreenEvent$MouseClickedEvent$Post":"net.minecraftforge.client.event.ScreenEvent$MouseClickedEvent$Post","be.florens.expandability.api.forge.LivingFluidCollisionEvent":"be.florens.expandability.api.forge.LivingFluidCollisionEvent","com.endertech.minecraft.forge.events.BlockStateChangeEvent":"com.endertech.minecraft.forge.events.BlockStateChangeEvent","net.minecraftforge.event.entity.EntityEvent$EntityConstructing":"net.minecraftforge.event.entity.EntityEvent$EntityConstructing","net.mrscauthd.beyond_earth.events.forge.RenderHandItemEvent$Post":"net.mrscauthd.beyond_earth.events.forge.RenderHandItemEvent$Post","net.minecraftforge.client.event.ScreenOpenEvent":"net.minecraftforge.client.event.ScreenOpenEvent","net.minecraftforge.client.event.RenderArmEvent":"net.minecraftforge.client.event.RenderArmEvent","net.minecraftforge.client.event.EntityViewRenderEvent$FogDensity":"net.minecraftforge.client.event.EntityViewRenderEvent$FogDensity","com.endertech.minecraft.forge.events.RandomTickEvent$Block":"com.endertech.minecraft.forge.events.RandomTickEvent$Block","net.minecraftforge.client.event.ScreenEvent$MouseDragEvent$Post":"net.minecraftforge.client.event.ScreenEvent$MouseDragEvent$Post","net.minecraftforge.event.entity.living.LivingDeathEvent":"net.minecraftforge.event.entity.living.LivingDeathEvent","me.desht.pneumaticcraft.api.drone.DroneConstructingEvent":"me.desht.pneumaticcraft.api.drone.DroneConstructingEvent","net.minecraftforge.event.entity.player.PlayerContainerEvent$Close":"net.minecraftforge.event.entity.player.PlayerContainerEvent$Close","net.minecraftforge.client.event.FOVModifierEvent":"net.minecraftforge.client.event.FOVModifierEvent","net.minecraftforge.event.entity.living.LivingDropsEvent":"net.minecraftforge.event.entity.living.LivingDropsEvent","net.minecraftforge.client.event.RenderPlayerEvent$Post":"net.minecraftforge.client.event.RenderPlayerEvent$Post","net.minecraftforge.client.event.RecipesUpdatedEvent":"net.minecraftforge.client.event.RecipesUpdatedEvent","net.minecraftforge.event.world.BiomeLoadingEvent":"net.minecraftforge.event.world.BiomeLoadingEvent","net.minecraftforge.event.entity.living.LivingSpawnEvent$SpecialSpawn":"net.minecraftforge.event.entity.living.LivingSpawnEvent$SpecialSpawn","net.minecraftforge.client.event.ScreenEvent$MouseDragEvent$Pre":"net.minecraftforge.client.event.ScreenEvent$MouseDragEvent$Pre","com.jozufozu.flywheel.event.BeginFrameEvent":"com.jozufozu.flywheel.event.BeginFrameEvent","net.minecraftforge.event.entity.player.PlayerNegotiationEvent":"net.minecraftforge.event.entity.player.PlayerNegotiationEvent","net.mrscauthd.beyond_earth.events.forge.LivingEntityTickEndEvent":"net.mrscauthd.beyond_earth.events.forge.LivingEntityTickEndEvent","com.jozufozu.flywheel.event.RenderLayerEvent":"com.jozufozu.flywheel.event.RenderLayerEvent","net.minecraftforge.event.TickEvent$PlayerTickEvent":"net.minecraftforge.event.TickEvent$PlayerTickEvent","net.minecraftforge.server.permission.events.PermissionGatherEvent$Handler":"net.minecraftforge.server.permission.events.PermissionGatherEvent$Handler","team.lodestar.lodestone.events.types.RightClickEmptyServer":"team.lodestar.lodestone.events.types.RightClickEmptyServer","net.minecraftforge.event.entity.player.PlayerEvent$TabListNameFormat":"net.minecraftforge.event.entity.player.PlayerEvent$TabListNameFormat","net.minecraftforge.event.entity.living.ZombieEvent$SummonAidEvent":"net.minecraftforge.event.entity.living.ZombieEvent$SummonAidEvent","com.endertech.minecraft.forge.events.ChunkFullyLoadedEvent":"com.endertech.minecraft.forge.events.ChunkFullyLoadedEvent","net.minecraftforge.event.entity.player.PlayerEvent$StartTracking":"net.minecraftforge.event.entity.player.PlayerEvent$StartTracking","net.mrscauthd.beyond_earth.events.forge.RenderHandItemEvent$Pre":"net.mrscauthd.beyond_earth.events.forge.RenderHandItemEvent$Pre","net.minecraftforge.client.event.InputEvent$KeyInputEvent":"net.minecraftforge.client.event.InputEvent$KeyInputEvent","slimeknights.tconstruct.library.events.MaterialsLoadedEvent":"slimeknights.tconstruct.library.events.MaterialsLoadedEvent","org.zeith.hammerlib.event.player.PlayerLoadedInEvent":"org.zeith.hammerlib.event.player.PlayerLoadedInEvent","net.minecraftforge.client.event.ScreenEvent$KeyboardCharTypedEvent$Pre":"net.minecraftforge.client.event.ScreenEvent$KeyboardCharTypedEvent$Pre","net.minecraftforge.event.entity.living.LivingSetAttackTargetEvent":"net.minecraftforge.event.entity.living.LivingSetAttackTargetEvent","net.minecraftforge.client.event.ClientChatReceivedEvent":"net.minecraftforge.client.event.ClientChatReceivedEvent","net.minecraftforge.client.event.EntityViewRenderEvent$FieldOfView":"net.minecraftforge.client.event.EntityViewRenderEvent$FieldOfView","net.minecraftforge.client.event.ScreenEvent$InitScreenEvent$Pre":"net.minecraftforge.client.event.ScreenEvent$InitScreenEvent$Pre","net.minecraftforge.client.event.RenderGameOverlayEvent$Pre":"net.minecraftforge.client.event.RenderGameOverlayEvent$Pre","com.anthonyhilyard.iceberg.events.RenderTooltipExtEvent$Post":"com.anthonyhilyard.iceberg.events.RenderTooltipExtEvent$Post","shadows.apotheosis.Apotheosis$ApotheosisReloadEvent":"shadows.apotheosis.Apotheosis$ApotheosisReloadEvent","net.minecraftforge.event.entity.living.PotionEvent$PotionAddedEvent":"net.minecraftforge.event.entity.living.PotionEvent$PotionAddedEvent","me.desht.pneumaticcraft.api.heat.HeatRegistrationEvent":"me.desht.pneumaticcraft.api.heat.HeatRegistrationEvent","net.minecraftforge.event.world.BlockEvent$CreateFluidSourceEvent":"net.minecraftforge.event.world.BlockEvent$CreateFluidSourceEvent","net.minecraftforge.client.event.sound.PlaySoundEvent":"net.minecraftforge.client.event.sound.PlaySoundEvent","net.minecraftforge.client.event.RenderTooltipEvent$Pre":"net.minecraftforge.client.event.RenderTooltipEvent$Pre","net.minecraftforge.event.CommandEvent":"net.minecraftforge.event.CommandEvent","com.anthonyhilyard.iceberg.events.CriterionEvent":"com.anthonyhilyard.iceberg.events.CriterionEvent","net.minecraftforge.client.event.RenderLivingEvent$Post":"net.minecraftforge.client.event.RenderLivingEvent$Post","net.minecraftforge.event.TickEvent$ServerTickEvent":"net.minecraftforge.event.TickEvent$ServerTickEvent","net.minecraftforge.client.event.ScreenEvent$KeyboardKeyPressedEvent$Pre":"net.minecraftforge.client.event.ScreenEvent$KeyboardKeyPressedEvent$Pre","net.minecraftforge.event.entity.living.PotionEvent$PotionRemoveEvent":"net.minecraftforge.event.entity.living.PotionEvent$PotionRemoveEvent","net.minecraftforge.event.entity.living.LivingFallEvent":"net.minecraftforge.event.entity.living.LivingFallEvent","net.minecraftforge.event.entity.player.PlayerXpEvent$XpChange":"net.minecraftforge.event.entity.player.PlayerXpEvent$XpChange","slimeknights.tconstruct.library.events.ToolEquipmentChangeEvent":"slimeknights.tconstruct.library.events.ToolEquipmentChangeEvent","net.minecraftforge.event.world.ChunkDataEvent$Save":"net.minecraftforge.event.world.ChunkDataEvent$Save","net.minecraftforge.event.entity.ProjectileImpactEvent":"net.minecraftforge.event.entity.ProjectileImpactEvent","net.minecraftforge.event.furnace.FurnaceFuelBurnTimeEvent":"net.minecraftforge.event.furnace.FurnaceFuelBurnTimeEvent","net.minecraftforge.event.AddReloadListenerEvent":"net.minecraftforge.event.AddReloadListenerEvent","net.minecraftforge.client.event.InputEvent$MouseInputEvent":"net.minecraftforge.client.event.InputEvent$MouseInputEvent","io.github.noeppi_noeppi.libx.event.ConfigLoadedEvent":"io.github.noeppi_noeppi.libx.event.ConfigLoadedEvent","io.github.noeppi_noeppi.libx.event.RandomTickEvent$Block":"io.github.noeppi_noeppi.libx.event.RandomTickEvent$Block","net.mrscauthd.beyond_earth.events.forge.BlockSetEvent":"net.mrscauthd.beyond_earth.events.forge.BlockSetEvent","net.minecraftforge.client.event.RenderHandEvent":"net.minecraftforge.client.event.RenderHandEvent","net.minecraftforge.event.world.BlockEvent$FluidPlaceBlockEvent":"net.minecraftforge.event.world.BlockEvent$FluidPlaceBlockEvent","net.mrscauthd.beyond_earth.events.forge.EntityTickEvent":"net.mrscauthd.beyond_earth.events.forge.EntityTickEvent","net.minecraftforge.client.event.RenderLivingEvent$Pre":"net.minecraftforge.client.event.RenderLivingEvent$Pre","net.minecraftforge.event.world.ChunkWatchEvent$Watch":"net.minecraftforge.event.world.ChunkWatchEvent$Watch","net.minecraftforge.event.server.ServerStartedEvent":"net.minecraftforge.event.server.ServerStartedEvent","net.minecraftforge.client.event.RenderNameplateEvent":"net.minecraftforge.client.event.RenderNameplateEvent","com.supermartijn642.core.render.RenderWorldEvent":"com.supermartijn642.core.render.RenderWorldEvent","vazkii.patchouli.api.BookDrawScreenEvent":"vazkii.patchouli.api.BookDrawScreenEvent","net.minecraftforge.event.entity.EntityJoinWorldEvent":"net.minecraftforge.event.entity.EntityJoinWorldEvent","net.minecraftforge.event.world.WorldEvent$PotentialSpawns":"net.minecraftforge.event.world.WorldEvent$PotentialSpawns","net.minecraftforge.client.event.ScreenEvent$KeyboardKeyReleasedEvent$Pre":"net.minecraftforge.client.event.ScreenEvent$KeyboardKeyReleasedEvent$Pre","net.minecraftforge.event.TickEvent$WorldTickEvent":"net.minecraftforge.event.TickEvent$WorldTickEvent","net.minecraftforge.client.event.RegisterClientCommandsEvent":"net.minecraftforge.client.event.RegisterClientCommandsEvent","net.minecraftforge.event.DifficultyChangeEvent":"net.minecraftforge.event.DifficultyChangeEvent","net.minecraftforge.event.entity.living.PotionEvent$PotionExpiryEvent":"net.minecraftforge.event.entity.living.PotionEvent$PotionExpiryEvent","net.minecraftforge.event.world.WorldEvent$Load":"net.minecraftforge.event.world.WorldEvent$Load","net.minecraftforge.event.entity.living.PotionColorCalculationEvent":"net.minecraftforge.event.entity.living.PotionColorCalculationEvent","net.minecraftforge.client.event.ClientChatEvent":"net.minecraftforge.client.event.ClientChatEvent","com.github.alexthe666.citadel.client.event.EventGetStarBrightness":"com.github.alexthe666.citadel.client.event.EventGetStarBrightness","net.minecraftforge.event.entity.living.LivingSpawnEvent$CheckSpawn":"net.minecraftforge.event.entity.living.LivingSpawnEvent$CheckSpawn","net.minecraftforge.event.server.ServerAboutToStartEvent":"net.minecraftforge.event.server.ServerAboutToStartEvent","net.mrscauthd.beyond_earth.events.forge.SetupLivingBipedAnimEvent$Post":"net.mrscauthd.beyond_earth.events.forge.SetupLivingBipedAnimEvent$Post","net.minecraftforge.event.entity.living.LivingDestroyBlockEvent":"net.minecraftforge.event.entity.living.LivingDestroyBlockEvent","net.minecraftforge.client.event.RenderLevelLastEvent":"net.minecraftforge.client.event.RenderLevelLastEvent","com.hollingsworth.arsnouveau.api.event.ManaRegenCalcEvent":"com.hollingsworth.arsnouveau.api.event.ManaRegenCalcEvent","vazkii.botania.api.mana.ManaItemsEvent":"vazkii.botania.api.mana.ManaItemsEvent","net.minecraftforge.event.village.WandererTradesEvent":"net.minecraftforge.event.village.WandererTradesEvent","com.endertech.minecraft.forge.events.CampfireSmokeEvent":"com.endertech.minecraft.forge.events.CampfireSmokeEvent","net.minecraftforge.event.entity.EntityEvent$Size":"net.minecraftforge.event.entity.EntityEvent$Size","net.minecraftforge.event.TickEvent$RenderTickEvent":"net.minecraftforge.event.TickEvent$RenderTickEvent","net.minecraftforge.client.event.ClientPlayerNetworkEvent$LoggedInEvent":"net.minecraftforge.client.event.ClientPlayerNetworkEvent$LoggedInEvent","net.minecraftforge.event.world.ChunkEvent$Load":"net.minecraftforge.event.world.ChunkEvent$Load","net.blay09.mods.cookingforblockheads.api.event.FoodRegistryInitEvent":"net.blay09.mods.cookingforblockheads.api.event.FoodRegistryInitEvent","sirttas.dpanvil.api.event.DataManagerReloadEvent":"sirttas.dpanvil.api.event.DataManagerReloadEvent","net.minecraftforge.event.world.ChunkDataEvent$Load":"net.minecraftforge.event.world.ChunkDataEvent$Load","net.minecraftforge.event.entity.living.PotionEvent$PotionApplicableEvent":"net.minecraftforge.event.entity.living.PotionEvent$PotionApplicableEvent","shadows.placebo.events.ItemUseEvent":"shadows.placebo.events.ItemUseEvent","net.minecraftforge.client.event.MovementInputUpdateEvent":"net.minecraftforge.client.event.MovementInputUpdateEvent","net.minecraftforge.event.entity.player.AdvancementEvent":"net.minecraftforge.event.entity.player.AdvancementEvent","net.minecraftforge.event.entity.player.PlayerInteractEvent$RightClickBlock":"net.minecraftforge.event.entity.player.PlayerInteractEvent$RightClickBlock","net.minecraftforge.client.event.ScreenEvent$MouseReleasedEvent$Pre":"net.minecraftforge.client.event.ScreenEvent$MouseReleasedEvent$Pre","net.mrscauthd.beyond_earth.events.forge.SetupLivingBipedAnimEvent$Pre":"net.mrscauthd.beyond_earth.events.forge.SetupLivingBipedAnimEvent$Pre","net.minecraftforge.event.entity.living.LivingAttackEvent":"net.minecraftforge.event.entity.living.LivingAttackEvent","net.minecraftforge.client.event.RenderGameOverlayEvent$Chat":"net.minecraftforge.client.event.RenderGameOverlayEvent$Chat","net.minecraftforge.client.event.ClientPlayerNetworkEvent$LoggedOutEvent":"net.minecraftforge.client.event.ClientPlayerNetworkEvent$LoggedOutEvent","net.minecraftforge.client.event.RenderLevelStageEvent":"net.minecraftforge.client.event.RenderLevelStageEvent","net.minecraftforge.client.event.ScreenEvent$DrawScreenEvent$Pre":"net.minecraftforge.client.event.ScreenEvent$DrawScreenEvent$Pre","net.minecraftforge.client.event.ScreenEvent$KeyboardKeyPressedEvent$Post":"net.minecraftforge.client.event.ScreenEvent$KeyboardKeyPressedEvent$Post","net.minecraftforge.server.permission.events.PermissionGatherEvent$Nodes":"net.minecraftforge.server.permission.events.PermissionGatherEvent$Nodes","net.minecraftforge.event.world.ChunkEvent$Unload":"net.minecraftforge.event.world.ChunkEvent$Unload","net.minecraftforge.event.entity.living.LivingPackSizeEvent":"net.minecraftforge.event.entity.living.LivingPackSizeEvent","net.minecraftforge.event.entity.living.LootingLevelEvent":"net.minecraftforge.event.entity.living.LootingLevelEvent","net.minecraftforge.event.entity.living.LivingEvent$LivingJumpEvent":"net.minecraftforge.event.entity.living.LivingEvent$LivingJumpEvent","net.minecraftforge.event.entity.player.PlayerFlyableFallEvent":"net.minecraftforge.event.entity.player.PlayerFlyableFallEvent","net.mehvahdjukaar.selene.resourcepack.EarlyPackReloadEvent":"net.mehvahdjukaar.selene.resourcepack.EarlyPackReloadEvent","net.minecraftforge.event.entity.living.LivingKnockBackEvent":"net.minecraftforge.event.entity.living.LivingKnockBackEvent","net.minecraftforge.event.LootTableLoadEvent":"net.minecraftforge.event.LootTableLoadEvent","net.minecraftforge.client.event.RenderGameOverlayEvent$PreLayer":"net.minecraftforge.client.event.RenderGameOverlayEvent$PreLayer","net.minecraftforge.event.entity.player.PlayerEvent$NameFormat":"net.minecraftforge.event.entity.player.PlayerEvent$NameFormat","shadows.apotheosis.Apotheosis$ApotheosisCommandEvent":"shadows.apotheosis.Apotheosis$ApotheosisCommandEvent","net.minecraftforge.event.entity.living.LivingEquipmentChangeEvent":"net.minecraftforge.event.entity.living.LivingEquipmentChangeEvent","net.minecraftforge.event.TickEvent$ClientTickEvent":"net.minecraftforge.event.TickEvent$ClientTickEvent","com.hollingsworth.arsnouveau.api.event.MaxManaCalcEvent":"com.hollingsworth.arsnouveau.api.event.MaxManaCalcEvent","net.minecraftforge.event.server.ServerStartingEvent":"net.minecraftforge.event.server.ServerStartingEvent","com.jozufozu.flywheel.event.ReloadRenderersEvent":"com.jozufozu.flywheel.event.ReloadRenderersEvent","net.minecraftforge.client.event.InputEvent$RawMouseEvent":"net.minecraftforge.client.event.InputEvent$RawMouseEvent","net.mrscauthd.beyond_earth.events.forge.ItemEntityTickEndEvent":"net.mrscauthd.beyond_earth.events.forge.ItemEntityTickEndEvent","net.minecraftforge.event.VanillaGameEvent":"net.minecraftforge.event.VanillaGameEvent","net.mrscauthd.beyond_earth.events.forge.RenderViewEvent":"net.mrscauthd.beyond_earth.events.forge.RenderViewEvent","net.minecraftforge.event.world.BlockEvent$CropGrowEvent$Pre":"net.minecraftforge.event.world.BlockEvent$CropGrowEvent$Pre","net.minecraftforge.event.world.BlockEvent$CropGrowEvent$Post":"net.minecraftforge.event.world.BlockEvent$CropGrowEvent$Post","net.minecraftforge.client.event.ScreenEvent$BackgroundDrawnEvent":"net.minecraftforge.client.event.ScreenEvent$BackgroundDrawnEvent","net.minecraftforge.client.event.RenderTooltipEvent$Color":"net.minecraftforge.client.event.RenderTooltipEvent$Color","net.minecraftforge.client.event.ContainerScreenEvent$DrawForeground":"net.minecraftforge.client.event.ContainerScreenEvent$DrawForeground","net.minecraftforge.client.event.RenderPlayerEvent$Pre":"net.minecraftforge.client.event.RenderPlayerEvent$Pre","net.minecraftforge.client.event.RenderGameOverlayEvent$Text":"net.minecraftforge.client.event.RenderGameOverlayEvent$Text","net.minecraftforge.client.event.ScreenEvent$KeyboardKeyReleasedEvent$Post":"net.minecraftforge.client.event.ScreenEvent$KeyboardKeyReleasedEvent$Post","com.endertech.minecraft.forge.events.RandomTickEvent$Fluid":"com.endertech.minecraft.forge.events.RandomTickEvent$Fluid","net.minecraftforge.event.entity.EntityEvent$EnteringSection":"net.minecraftforge.event.entity.EntityEvent$EnteringSection","net.minecraftforge.event.AttachCapabilitiesEvent":"net.minecraftforge.event.AttachCapabilitiesEvent","net.minecraftforge.event.ItemAttributeModifierEvent":"net.minecraftforge.event.ItemAttributeModifierEvent","net.minecraftforge.client.event.RenderTooltipEvent$GatherComponents":"net.minecraftforge.client.event.RenderTooltipEvent$GatherComponents","net.minecraftforge.event.entity.living.LivingHurtEvent":"net.minecraftforge.event.entity.living.LivingHurtEvent","net.minecraftforge.client.event.sound.PlaySoundSourceEvent":"net.minecraftforge.client.event.sound.PlaySoundSourceEvent","net.minecraftforge.event.world.BlockEvent$NeighborNotifyEvent":"net.minecraftforge.event.world.BlockEvent$NeighborNotifyEvent","net.minecraftforge.client.event.ScreenEvent$InitScreenEvent$Post":"net.minecraftforge.client.event.ScreenEvent$InitScreenEvent$Post","net.blay09.mods.waystones.api.KnownWaystonesEvent":"net.blay09.mods.waystones.api.KnownWaystonesEvent","net.minecraftforge.event.entity.living.LivingEvent$LivingUpdateEvent":"net.minecraftforge.event.entity.living.LivingEvent$LivingUpdateEvent"}