{                 
  "type": "geolosys:deposit_dense",
  "config": {
    "yMin": -40,
    "yMax": 40,
    "size": 20,
    "dimensions": {
      "isBlacklist": false,
      "filter": [ "overworld" ]
    },
    "blockStateMatchers": [ "minecraft:stone" ],
    "blocks": {
      "default": [{
        "block": "minecraft:iron_ore",
        "chance": 0.6
      },{
        "block": "minecraft:gold_ore",
        "chance": 0.3
      },{
        "block": "thermal:sulfur_ore",
        "chance": 0.1
      }],
      "minecraft:deepslate": [{
        "block": "minecraft:deepslate_iron_ore",
        "chance": 0.6
      },{
        "block": "minecraft:deepslate_gold_ore",
        "chance": 0.3
      },{
        "block": "thermal:deepslate_sulfur_ore",
        "chance": 0.1
      }]
    },
    "samples": [{
      "block": "minecraft:air",
      "chance": 1.0
    }],
    "generationWeight": 5
  }
}